sync_music/__init__.py
sync_music/__main__.py
sync_music/copy.py
sync_music/hashdb.py
sync_music/metadata.py
sync_music/replaygain.py
sync_music/sync_music.py
sync_music/transcode.py
sync_music/util.py
sync_music-0.5.1.dist-info/METADATA
sync_music-0.5.1.dist-info/WHEEL
sync_music-0.5.1.dist-info/entry_points.txt
sync_music-0.5.1.dist-info/licenses/LICENSE
sync_music-0.5.1.dist-info/RECORD
