Metadata-Version: 2.4
Name: sync_music
Version: 0.5.1
Summary: Sync music library to external devices
Project-URL: Repository, https://github.com/fetzerch/sync_music
Author-email: Christian Fetzer <fetzer.ch@gmail.com>
License-Expression: GPL-2.0-or-later
License-File: LICENSE
Keywords: music,synchronization
Classifier: Development Status :: 4 - Beta
Classifier: Environment :: Console
Classifier: Intended Audience :: End Users/Desktop
Classifier: Natural Language :: English
Classifier: Operating System :: POSIX
Classifier: Programming Language :: Python
Classifier: Topic :: Multimedia :: Sound/Audio :: Conversion
Classifier: Topic :: System :: Systems Administration
Requires-Python: >=3.9
Requires-Dist: mutagen>=1.29
